etlite/__init__.py
etlite/delim.py
etlite/exceptions.py
etlite-0.1.1.dist-info/METADATA
etlite-0.1.1.dist-info/WHEEL
etlite-0.1.1.dist-info/top_level.txt
etlite-0.1.1.dist-info/RECORD
