Metadata-Version: 2.1
Name: etlite
Version: 0.1.1
Summary: Extract/Transform Light - a simple library for reading delimited files.
Home-page: https://github.com/shelldweller/etlite
Author: Sergiy Kuzmenko
License: Public Domain
Platform: any
Classifier: Development Status :: 4 - Beta
Classifier: License :: Public Domain
Classifier: Programming Language :: Python :: 2
Classifier: Programming Language :: Python :: 3
Classifier: Topic :: Software Development :: Interpreters
